customer_prediction/__init__.py
customer_prediction/chart/__init__.py
customer_prediction/chart/chart.py
customer_prediction/clv/__init__.py
customer_prediction/clv/clv.py
customer_prediction/ltv/__init__.py
customer_prediction/ltv/ltv.py
customer_prediction/model/__init__.py
customer_prediction/model/cross_validation.py
customer_prediction/model/grid_search.py
customer_prediction/model/model_util.py
customer_prediction/preprocessing_util/__init__.py
customer_prediction/preprocessing_util/preprocessing.py
customer_prediction/util/__init__.py
customer_prediction/util/validation.py
customer_prediction-0.0.2.dist-info/LICENSE
customer_prediction-0.0.2.dist-info/METADATA
customer_prediction-0.0.2.dist-info/WHEEL
customer_prediction-0.0.2.dist-info/top_level.txt
customer_prediction-0.0.2.dist-info/RECORD
