Metadata-Version: 2.1
Name: customer-prediction
Version: 0.0.2
Summary: Library to work with customers prediction
Home-page: https://github.com/pypa/sampleproject
Author: Valery Bychkova
Author-email: valerybychkova@tut.by
License: UNKNOWN
Project-URL: Bug Tracker, https://github.com/pypa/sampleproject/issues
Platform: UNKNOWN
Classifier: Programming Language :: Python :: 3
Classifier: License :: OSI Approved :: MIT License
Classifier: Operating System :: OS Independent
Requires-Python: >=3.6
License-File: LICENSE
